punigowdaa/__init__.py
punigowdaa/genai_programs.py
punigowdaa-0.1.dist-info/METADATA
punigowdaa-0.1.dist-info/WHEEL
punigowdaa-0.1.dist-info/licenses/LICENSE
punigowdaa-0.1.dist-info/RECORD
