Metadata-Version: 2.4
Name: punigowdaa
Version: 0.1
Summary: A simple example package
Project-URL: Homepage, https://github.com/yourusername/punigowda
Project-URL: Bug Tracker, https://github.com/yourusername/punigowda/issues
Author-email: puneeth <puneethmgowda047@email.com>
License-File: LICENSE
Classifier: License :: OSI Approved :: MIT License
Classifier: Operating System :: OS Independent
Classifier: Programming Language :: Python :: 3
Requires-Python: >=3.6
